chartkra/__init__.py
chartkra/__init__.pyc
chartkra/chartkra.py
chartkra/heatmap.py
chartkra/__pycache__/__init__.cpython-36.pyc
chartkra-0.0.7.dist-info/DESCRIPTION.rst
chartkra-0.0.7.dist-info/METADATA
chartkra-0.0.7.dist-info/RECORD
chartkra-0.0.7.dist-info/WHEEL
chartkra-0.0.7.dist-info/metadata.json
chartkra-0.0.7.dist-info/top_level.txt
chartkra-0.0.7.dist-info/zip-safe
