Metadata-Version: 2.0
Name: chartkra
Version: 0.0.7
Summary: chartkra
Home-page: https://github.com/KazafChen
Author: Kazaf Chen
Author-email: kazaf.chen@gmail.com
License: MIT
Keywords: chartkra
Platform: UNKNOWN
Classifier: License :: OSI Approved :: MIT License
Classifier: Programming Language :: Python
Classifier: Intended Audience :: Developers
Classifier: Operating System :: OS Independent
